Metadata-Version: 2.1
Name: synapseformation
Version: 0.0.2
Summary: Client for using Synapse Formation templates.
Home-page: https://github.com/Sage-Bionetworks/synapseformation
Author: Kenneth Daily,Thomas Yu,Kelsey Montgomery
License: Apache
Project-URL: Documentation, https://github.com/Sage-Bionetworks/synapseformation
Project-URL: Source Code, https://github.com/Sage-Bionetworks/synapseformation
Project-URL: Bug Tracker, https://github.com/Sage-Bionetworks/synapseformation/issues
Platform: UNKNOWN
Classifier: Development Status :: 5 - Production/Stable
Classifier: Programming Language :: Python
Classifier: Programming Language :: Python :: 3.6
Classifier: Programming Language :: Python :: 3.7
Classifier: Programming Language :: Python :: 3.8
Classifier: Programming Language :: Python :: 3.9
Classifier: Operating System :: MacOS
Classifier: Operating System :: Microsoft :: Windows
Classifier: Operating System :: Unix
Classifier: Operating System :: POSIX :: Linux
Classifier: Intended Audience :: Developers
Classifier: Intended Audience :: Science/Research
Classifier: License :: OSI Approved :: Apache Software License
Classifier: Topic :: Software Development :: Libraries
Classifier: Topic :: Scientific/Engineering
Classifier: Topic :: Scientific/Engineering :: Bio-Informatics
Requires-Python: >=3.6
